{
	"song": {
		"speed": 2.8,
		"stage": "iceolation",
		"player1": "zerktro-player",
		"player2": "iceolation",
		"instVol": 1,
		"events": [
			[
				0,
				[
					[
						"Mid Snow",
						"1",
						"47"
					]
				]
			],
			[
				43885.7142857143,
				[
					[
						"Screen Shake",
						"1.71, 0.02",
						""
					]
				]
			],
			[
				43971.4285714286,
				[
					[
						"Change Scroll Speed",
						"1",
						"3"
					]
				]
			],
			[
				45514.2857142857,
				[
					[
						"Screen Shake",
						"10.8, 0.002",
						""
					]
				]
			],
			[
				45600,
				[
					[
						"Flash",
						"game",
						"0.5"
					]
				]
			],
			[
				45685.7142857143,
				[
					[
						"Strong Snow",
						"1",
						"0"
					]
				]
			],
			[
				56571.4285714286,
				[
					[
						"Screen Shake",
						"10.85, 0.001",
						""
					]
				]
			],
			[
				67542.8571428572,
				[
					[
						"Screen Shake",
						"5.48, 0.002",
						""
					]
				]
			],
			[
				73028.5714285714,
				[
					[
						"Screen Shake",
						"5.48, 0.001",
						""
					]
				]
			],
			[
				78514.2857142857,
				[
					[
						"Screen Shake",
						"5.48, 0.002",
						""
					]
				]
			],
			[
				83999.9999999999,
				[
					[
						"Screen Shake",
						"5.48, 0.001",
						""
					]
				]
			],
			[
				89485.7142857142,
				[
					[
						"Screen Shake",
						"10.97, 0.002",
						""
					]
				]
			],
			[
				100457.142857143,
				[
					[
						"Screen Shake",
						"10.97, 0.001",
						""
					]
				]
			],
			[
				111085.714285714,
				[
					[
						"Change Scroll Speed",
						"0.9",
						"5"
					]
				]
			],
			[
				111428.571428571,
				[
					[
						"Snowstorm",
						"0.4",
						"2"
					]
				]
			],
			[
				131914.285714285,
				[
					[
						"Change Scroll Speed",
						"1.1",
						"2"
					]
				]
			],
			[
				132000,
				[
					[
						"Screen Shake",
						"1.71, 0.02",
						""
					],
					[
						"Set Default Zoom",
						"0.75",
						""
					],
					[
						"Camera Follow Pos",
						"-150",
						"200"
					]
				]
			],
			[
				132085.714285714,
				[
					[
						"Snowstorm",
						"0",
						"1.25"
					]
				]
			],
			[
				133028.571428571,
				[
					[
						"Weak Snow",
						"1",
						"0"
					]
				]
			],
			[
				133114.285714285,
				[
					[
						"Mid Snow",
						"1",
						"0"
					]
				]
			],
			[
				133200,
				[
					[
						"Strong Snow",
						"1",
						"0"
					],
					[
						"Play Animation",
						"singRIGHT",
						"iceolation"
					]
				]
			],
			[
				133285.714285714,
				[
					[
						"Set Default Zoom",
						"0.5",
						""
					],
					[
						"Flash",
						"game",
						"1"
					],
					[
						"Add Camera Zoom",
						"-0.25",
						""
					],
					[
						"Snowstorm",
						"0.4",
						"0.0001"
					]
				]
			],
			[
				133371.428571428,
				[
					[
						"Snowy Stage",
						"",
						""
					],
					[
						"Camera Follow Pos",
						"",
						""
					]
				]
			],
			[
				133457.142857143,
				[
					[
						"Screen Shake",
						"10.88, 0.001",
						""
					]
				]
			],
			[
				133542.857142857,
				[
					[
						"Strongest Snow",
						"1",
						"0"
					]
				]
			],
			[
				144342.857142857,
				[
					[
						"Screen Shake",
						"10.97, 0.002",
						""
					]
				]
			],
			[
				155314.285714286,
				[
					[
						"Screen Shake",
						"10.97, 0.001",
						""
					]
				]
			],
			[
				166285.714285714,
				[
					[
						"Screen Shake",
						"10.97, 0.002",
						""
					]
				]
			],
			[
				177257.142857143,
				[
					[
						"Screen Shake",
						"21.93, 0.002",
						""
					]
				]
			],
			[
				199200,
				[
					[
						"Screen Shake",
						"2.75, 0.001",
						""
					]
				]
			],
			[
				201942.857142857,
				[
					[
						"Strong Snow",
						"0",
						"5"
					]
				]
			],
			[
				202028.571428572,
				[
					[
						"Strongest Snow",
						"0",
						"5"
					],
					[
						"Snowstorm",
						"0",
						"1.25"
					]
				]
			]
		],
		"arrowSkinbf": null,
		"notes": [],
		"splashSkin": null,
		"validScore": false,
		"gfVersion": "gf",
		"arrowSkindad": null,
		"bpm": 175,
		"needsVoices": true,
		"vocalVol": 1,
		"song": "Icebreaker"
	}
}
